mytest/ic競賽/2016初賽/mytest/LBP.v
`timescale 1ns/10ps
module LBP ( clk, reset, gray_addr, gray_req, gray_ready, gray_data, lbp_addr, lbp_valid, lbp_data, finish);
    input   	    clk;
    input   	    reset;
    output  [13:0] 	gray_addr;
    output         	gray_req;
    input   	    gray_ready;
    input   [7:0] 	gray_data;
    output  [13:0] 	lbp_addr;
    output  	    lbp_valid;
    output  [7:0] 	lbp_data;
    output  	    finish;
    /**********************************************************************
                                declaration
    **********************************************************************/
    reg [13:0]  gray_addr;//ok
    reg         gray_req;//ok
    reg [13:0]  lbp_addr;
    reg         lbp_valid;//ok
    reg [7:0]   lbp_data;
    reg         finish;

    reg [1:0]   state_cr;
    reg [1:0]   state_nt;
    parameter   READ = 0;
    parameter   CALC = 1;
    parameter   WRITE = 2;

    reg [7:0]   img_buf     [0:16383];
    reg [7:0]   thrshld     [0:16383];
    wire [7:0]  cent;
    reg [13:0]  cent_point;
    reg         g7; 
    reg         g6;
    reg         g5;
    reg         g4;
    reg         g3;
    reg         g2;
    reg         g1;
    reg         g0;
    integer i;
//==============================================================================================================
     /*********************************************************************
                                 state machine    
    **********************************************************************/
    always@(posedge reset or posedge clk)begin
        if(reset)
            state_cr <= READ;
        else  
            state_cr <= state_nt;
    end
    
    always@(*)begin
        if(reset)begin
            state_nt = READ;
        end
        else begin
            case(state_cr)
                READ:begin
                    if(gray_addr == 14'd16383)
                        state_nt = CALC;
                    else
                        state_nt = READ;
                end
                CALC:begin
                    if(cent_point == 14'd16254)
                        state_nt = WRITE;
                    else
                        state_nt = CALC;
                end
                WRITE:begin
                    state_nt = WRITE;
                end
                default:begin
                    state_nt = READ;
                end
            endcase
        end
    end

    /**********************************************************************
                                    state output    
    **********************************************************************/
    always@(*)begin
        case(state_cr)
            READ:begin
                gray_req = 1'b1;
                lbp_valid = 1'b0;
            end
            CALC:begin
                gray_req = 1'b0;
                lbp_valid = 1'b0;
            end
            WRITE:begin
                gray_req = 1'b0;
                lbp_valid = 1'b1;
            end
            default:begin
                gray_req = 1'b0;
                lbp_valid = 1'b0;
            end
        endcase
    end
    /**********************************************************************
                                  gray_addr    
    **********************************************************************/
    always@(posedge reset or negedge clk)begin
        if(reset)
            gray_addr <= 14'd0;
        else if(gray_ready)begin
            if(gray_addr == 14'd16383)
                gray_addr <= gray_addr;
            else
                gray_addr <= gray_addr + 14'd1;
        end
        else begin
            gray_addr <= gray_addr;
        end
    end
    /**********************************************************************
                                  img_buf    
    **********************************************************************/
    always@(posedge clk)begin
        case(state_cr)
            READ:begin
                img_buf[gray_addr] <= gray_data;
            end
            CALC:begin
                //img_buf <= img_buf;
            end
            WRITE:begin
                //img_buf <= img_buf;
            end    
            default:begin
                //img_buf <= img_buf;
            end 
        endcase

        /*
        if(gray_ready)
            img_buf[gray_addr] <= gray_data;
        else if (lbp_valid)
            img_buf <= thrshld;
        else
            img_buf <= img_buf;
        */
    end
    /**********************************************************************
                                  thrshld    
    **********************************************************************/
    
    always@(posedge reset or posedge clk)begin
        if(reset)begin
            for(i = 0; i < 16384; i = i + 1)
                thrshld[i] <= 8'd0;
        end  
        else begin  
            case(state_cr)
                READ:begin
                    //thrshld <= thrshld;
                end
                CALC:begin
                    thrshld[cent_point] <= cent;
                end
                WRITE:begin
                    //thrshld <= thrshld;
                end
            endcase
        end
    end

    //cent point
    always@(posedge clk)begin
        if(reset)
            cent_point <= 14'd128;
        else begin
            case(state_cr)
                READ:begin
                    cent_point <= cent_point;
                end
                CALC:begin
                    if(cent_point == 14'd16254)
                        cent_point <= cent_point;
                    else if(cent_point % 14'd128 == 14'd126)
                        cent_point <= cent_point + 14'd3;
                    else
                        cent_point <= cent_point + 14'd1;
                end
                WRITE:begin
                        cent_point <= cent_point;
                end
            endcase
        end
    end

    //side point calculate
    always@(*)begin
        if (cent_point >= 14'd129)  g0 = (img_buf[cent_point - 14'd129] >= img_buf[cent_point]) ? 1'b1 : 1'b0;
        else g0 = 1'b0;

        if (cent_point >= 14'd128)  g1 = (img_buf[cent_point - 14'd128] >= img_buf[cent_point]) ? 1'b1 : 1'b0;
        else g1 = 1'b0;

        if (cent_point >= 14'd127)  g2 = (img_buf[cent_point - 14'd127] >= img_buf[cent_point]) ? 1'b1 : 1'b0;
        else g2 = 1'b0;

        if (cent_point >= 14'd1)  g3 = (img_buf[cent_point - 14'd1] >= img_buf[cent_point]) ? 1'b1 : 1'b0;
        else g3 = 1'b0;

        if (cent_point <= 14'd16382)  g4 = (img_buf[cent_point + 14'd1] >= img_buf[cent_point]) ? 1'b1 : 1'b0;
        else g4 = 1'b0;
        
        if (cent_point <= 14'd16256)  g5 = (img_buf[cent_point + 14'd127] >= img_buf[cent_point]) ? 1'b1 : 1'b0;
        else g5 = 1'b0;

        if (cent_point <= 14'd16255)  g6 = (img_buf[cent_point + 14'd128] >= img_buf[cent_point]) ? 1'b1 : 1'b0;
        else g6 = 1'b0;

        if (cent_point <= 14'd16254)  g7 = (img_buf[cent_point + 14'd129] >= img_buf[cent_point]) ? 1'b1 : 1'b0;
        else g7 = 1'b0;
    end

    assign cent = {g7, g6, g5, g4, g3, g2, g1, g0};

    /**********************************************************************
                                  lbp_addr    
    **********************************************************************/
    always@(posedge reset or posedge clk)begin
        if(reset)
            lbp_addr <= 14'd128;
        else if(lbp_valid)begin
            if(lbp_addr == 14'd16254)
                lbp_addr <= lbp_addr;
            else
                lbp_addr <= lbp_addr + 14'd1;
        end
        else begin
            lbp_addr <= lbp_addr;
        end
    end
    /**********************************************************************
                                  lbp_data    
    **********************************************************************/
    always@(posedge clk)begin
        if(lbp_valid)
            lbp_data <= thrshld[lbp_addr];
        else
            lbp_data <= lbp_data;
    end
    /**********************************************************************
                                  finish    
    **********************************************************************/
    always@(posedge clk)begin
        if(lbp_addr == 14'd16254)
            finish <= 1'b1;
        else
            finish <= 1'b0;
    end

//====================================================================
endmodule

my note/ic競賽/2016初賽/mytest/testfixture.v
`timescale 1ns/10ps

`include "LBP.v"

`define CYCLE      12.5          	  // Modify your clock period here
`define SDFFILE    "./SYN/LBP_syn.sdf"	  // Modify your sdf file name
`define End_CYCLE  100000000000              // Modify cycle times once your design need more cycle times!

`define PAT        "./pattern1.dat"    
`define EXP        "./golden1.dat"     


module testfixture;

parameter N_EXP   = 16384; // 128 x 128 pixel
parameter N_PAT   = N_EXP;

reg   [7:0]   gray_mem   [0:N_PAT-1];
reg   [7:0]   exp_mem    [0:N_EXP-1];

reg [7:0] LBP_dbg;
reg [7:0] exp_dbg;
wire [7:0] lbp_data;
reg   clk = 0;
reg   reset = 0;
reg   result_compare = 0;

integer err = 0;
integer times = 0;
reg over = 0;
integer exp_num = 0;
wire [13:0] gray_addr;
wire [13:0] lbp_addr;
reg [7:0] gray_data;
reg gray_ready = 0;
integer i;

   LBP LBP( .clk(clk), .reset(reset), 
            .gray_addr(gray_addr), .gray_req(gray_req), .gray_ready(gray_ready), .gray_data(gray_data), 
			.lbp_addr(lbp_addr), .lbp_valid(lbp_valid), .lbp_data(lbp_data), .finish(finish));
			
   lbp_mem u_lbp_mem(.lbp_valid(lbp_valid), .lbp_data(lbp_data), .lbp_addr(lbp_addr), .clk(clk));
   

`ifdef SDF
	initial $sdf_annotate(`SDFFILE, LBP);
`endif

initial	$readmemh (`PAT, gray_mem);
//initial	$readmemh (`EXP, exp_mem);

always begin #(`CYCLE/2) clk = ~clk; end

/*
initial begin
	$fsdbDumpfile("LBP.fsdb");
	$fsdbDumpvars;
end
*/

initial begin  // data input
   @(negedge clk)  reset = 1'b1; 
   #(`CYCLE*2);    reset = 1'b0; 
   @(negedge clk)  gray_ready = 1'b1;
    while (finish == 0) begin             
      if( gray_req ) begin
         gray_data = gray_mem[gray_addr];  
      end 
      else begin
         gray_data = 'hz;  
      end                    
      @(negedge clk); 
    end     
    gray_ready = 0; gray_data='hz;
	@(posedge clk) result_compare = 1; 
end

initial begin // result compare
	$display("-----------------------------------------------------\n");
 	$display("START!!! Simulation Start .....\n");
 	$display("-----------------------------------------------------\n");
	#(`CYCLE*3); 
	wait( finish ) ;
	@(posedge clk); @(posedge clk);
	for (i=0; i <N_PAT ; i=i+1) begin
			//@(posedge clk);  // TRY IT ! no comment this line for debugging !!
				exp_dbg = exp_mem[i]; LBP_dbg = u_lbp_mem.LBP_M[i];
				if (exp_mem[i] == u_lbp_mem.LBP_M[i]) begin
					err = err;
				end
				else begin
					//$display("pixel %d is FAIL !!", i); 
					err = err+1;
					if (err <= 10) $display("Output pixel %d are wrong!", i);
					if (err == 11) begin $display("Find the wrong pixel reached a total of more than 10 !, Please check the code .....\n");  end
				end
				if( ((i%1000) === 0) || (i == 16383))begin  
					if ( err === 0)
      					$display("Output pixel: 0 ~ %d are correct!\n", i);
					else
					$display("Output Pixel: 0 ~ %d are wrong ! The wrong pixel reached a total of %d or more ! \n", i, err);
					
  				end					
				exp_num = exp_num + 1;
	end
	over = 1;
end


initial  begin
 #`End_CYCLE ;
 	$display("-----------------------------------------------------\n");
 	$display("Error!!! Somethings' wrong with your code ...!\n");
 	$display("-------------------------FAIL------------------------\n");
 	$display("-----------------------------------------------------\n");
 	$finish;
end

initial begin
      @(posedge over)      
      if((over) && (exp_num!='d0)) begin
         $display("-----------------------------------------------------\n");
         if (err == 0)  begin
            $display("Congratulations! All data have been generated successfully!\n");
            $display("-------------------------PASS------------------------\n");
         end
         else begin
            $display("There are %d errors!\n", err);
            $display("-----------------------------------------------------\n");
	    
         end
      end
      #(`CYCLE/2); $finish;
end
   
initial begin
	$dumpfile("wave.vcd");
	$dumpvars(0, testfixture);
end

endmodule


module lbp_mem (lbp_valid, lbp_data, lbp_addr, clk);
input		lbp_valid;
input	[13:0] 	lbp_addr;
input	[7:0]	lbp_data;
input		clk;

reg [7:0] LBP_M [0:16383];
integer i;

initial begin
	for (i=0; i<=16383; i=i+1) LBP_M[i] = 0;
end

always@(negedge clk) 
	if (lbp_valid) LBP_M[ lbp_addr ] <= lbp_data;

endmodule

mytest/ic競賽/2016初賽/mytest/wave.vcd
$date
	Wed Feb 12 16:04:51 2025
$end
$version
	Icarus Verilog
$end
$timescale
	10ps
$end
$scope module testfixture $end
$var wire 1 ! lbp_valid $end
$var wire 8 " lbp_data [7:0] $end
$var wire 14 # lbp_addr [13:0] $end
$var wire 1 $ gray_req $end
$var wire 14 % gray_addr [13:0] $end
$var wire 1 & finish $end
$var parameter 32 ' N_EXP $end
$var parameter 32 ( N_PAT $end
$var reg 8 ) LBP_dbg [7:0] $end
$var reg 1 * clk $end
$var reg 8 + exp_dbg [7:0] $end
$var reg 8 , gray_data [7:0] $end
$var reg 1 - gray_ready $end
$var reg 1 . over $end
$var reg 1 / reset $end
$var reg 1 0 result_compare $end
$var integer 32 1 err [31:0] $end
$var integer 32 2 exp_num [31:0] $end
$var integer 32 3 i [31:0] $end
$var integer 32 4 times [31:0] $end
$scope module LBP $end
$var wire 1 * clk $end
$var wire 8 5 gray_data [7:0] $end
$var wire 1 - gray_ready $end
$var wire 1 / reset $end
$var wire 8 6 cent [7:0] $end
$var parameter 32 7 CALC $end
$var parameter 32 8 READ $end
$var parameter 32 9 WRITE $end
$var reg 14 : cent_point [13:0] $end
$var reg 1 & finish $end
$var reg 1 ; g0 $end
$var reg 1 < g1 $end
$var reg 1 = g2 $end
$var reg 1 > g3 $end
$var reg 1 ? g4 $end
$var reg 1 @ g5 $end
$var reg 1 A g6 $end
$var reg 1 B g7 $end
$var reg 14 C gray_addr [13:0] $end
$var reg 1 $ gray_req $end
$var reg 14 D lbp_addr [13:0] $end
$var reg 8 E lbp_data [7:0] $end
$var reg 1 ! lbp_valid $end
$var reg 2 F state_cr [1:0] $end
$var reg 2 G state_nt [1:0] $end
$var integer 32 H i [31:0] $end
$upscope $end
$scope module u_lbp_mem $end
$var wire 1 * clk $end
$var wire 14 I lbp_addr [13:0] $end
$var wire 8 J lbp_data [7:0] $end
$var wire 1 ! lbp_valid $end
$var integer 32 K i [31:0] $end
$upscope $end
$upscope $end
$enddefinitions $end
$comment Show the parameter values. $end
$dumpall
b10 9
b0 8
b1 7
b100000000000000 (
b100000000000000 '
$end
#0
$dumpvars
b100000000000000 K
bx J
bx I
bx H
b0 G
bx F
bx E
bx D
bx C
xB
xA
x@
x?
x>
x=
x<
x;
bx :
bx 6
bx 5
b0 4
bx 3
b0 2
b0 1
00
0/
0.
0-
bx ,
bx +
0*
bx )
x&
bx %
x$
bx #
bx "
x!
$end
#625
0!
1$
0&
b0 F
1*
#1250
b10000000 #
b10000000 D
b10000000 I
b0 %
b0 C
b100000000000000 H
1/
0*
#1875
b10000001 :
b100000000000000 H
1*
#2500
0*
#3125
b100000000000000 H
1*
#3750
b1 %
b1 C
b10100010 ,
b10100010 5
1-
0*
0/
#4375
1*
#5000
b10 %
b10 C
b10100001 ,
b10100001 5
0*
#5625
1*
#6250
b11 %
b11 C
0*
#6875
1*
#7500
b100 %
b100 C
b10011110 ,
b10011110 5
0*
#8125
1*
#8750
b101 %
b101 C
b10011111 ,
b10011111 5
0*
#9375
1*
#10000
b110 %
b110 C
b10011100 ,
b10011100 5
0*
#10625
1*
#11250
b111 %
b111 C
b10011011 ,
b10011011 5
0*
#11875
1*
#12500
b1000 %
b1000 C
0*
#13125
1*
#13750
b1001 %
b1001 C
b10011100 ,
b10011100 5
0*
#14375
1*
#15000
b1010 %
b1010 C
b10100011 ,
b10100011 5
0*
#15625
1*
#16250
b1011 %
b1011 C
b10101000 ,
b10101000 5
0*
#16875
1*
#17500
b1100 %
b1100 C
b10101101 ,
b10101101 5
0*
#18125
1*
#18750
b1101 %
b1101 C
b10101100 ,
b10101100 5
0*
#19375
1*
#20000
b1110 %
b1110 C
b10100100 ,
b10100100 5
0*
#20625
1*
#21250
b1111 %
b1111 C
b10010100 ,
b10010100 5
0*
#21875
1*
#22500
b10000 %
b10000 C
b1110110 ,
b1110110 5
0*
#23125
1*
#23750
b10001 %
b10001 C
b1100000 ,
b1100000 5
0*
#24375
1*
#25000
b10010 %
b10010 C
0*
#25625
1*
#26250
b10011 %
b10011 C
b1100111 ,
b1100111 5
0*
#26875
1*
#27500
b10100 %
b10100 C
b1101010 ,
b1101010 5
0*
#28125
1*
#28750
b10101 %
b10101 C
b1101011 ,
b1101011 5
0*
#29375
1*
#30000
b10110 %
b10110 C
b1101100 ,
b1101100 5
0*
#30625
1*
#31250
b10111 %
b10111 C
0*
#31875
1*
#32500
b11000 %
b11000 C
b1101101 ,
b1101101 5
0*
#33125
1*
#33750
b11001 %
b11001 C
0*
#34375
1*
#35000
b11010 %
b11010 C
b1101010 ,
b1101010 5
0*
#35625
1*
#36250
b11011 %
b11011 C
b1110000 ,
b1110000 5
0*
#36875
1*
#37500
b11100 %
b11100 C
b1110110 ,
b1110110 5
0*
#38125
1*
#38750
b11101 %
b11101 C
b1110111 ,
b1110111 5
0*
#39375
1*
#40000
b11110 %
b11110 C
b1111011 ,
b1111011 5
0*
#40625
1*
#41250
b11111 %
b11111 C
b1111111 ,
b1111111 5
0*
#41875
1*
#42500
b100000 %
b100000 C
b10000001 ,
b10000001 5
0*
#43125
1*
#43750
b100001 %
b100001 C
b10000011 ,
b10000011 5
0*
#44375
1*
#45000
b100010 %
b100010 C
b10000001 ,
b10000001 5
0*
#45625
1*
#46250
b100011 %
b100011 C
b10000110 ,
b10000110 5
0*
#46875
1*
#47500
b100100 %
b100100 C
b10000010 ,
b10000010 5
0*
#48125
1*
#48750
b100101 %
b100101 C
b10000001 ,
b10000001 5
0*
#49375
1*
#50000
b100110 %
b100110 C
b10000011 ,
b10000011 5
0*
#50625
1*
#51250
b100111 %
b100111 C
b10000001 ,
b10000001 5
0*
#51875
1*
#52500
b101000 %
b101000 C
b10000110 ,
b10000110 5
0*
#53125
1*
#53750
b101001 %
b101001 C
b10000100 ,
b10000100 5
0*
#54375
1*
#55000
b101010 %
b101010 C
b10000110 ,
b10000110 5
0*
#55625
1*
#56250
b101011 %
b101011 C
b10000101 ,
b10000101 5
0*
#56875
1*
#57500
b101100 %
b101100 C
0*
#58125
1*
#58750
b101101 %
b101101 C
b10000110 ,
b10000110 5
0*
#59375
1*
#60000
b101110 %
b101110 C
b10000100 ,
b10000100 5
0*
#60625
1*
#61250
b101111 %
b101111 C
b10000111 ,
b10000111 5
0*
#61875
1*
#62500
b110000 %
b110000 C
b10000101 ,
b10000101 5
0*
#63125
1*
#63750
b110001 %
b110001 C
b10000110 ,
b10000110 5
0*
#64375
1*
#65000
b110010 %
b110010 C
b10001000 ,
b10001000 5
0*
#65625
1*
#66250
b110011 %
b110011 C
b10000111 ,
b10000111 5
0*
#66875
1*
#67500
b110100 %
b110100 C
b10000110 ,
b10000110 5
0*
#68125
1*
#68750
b110101 %
b110101 C
b10001000 ,
b10001000 5
0*
#69375
1*
#70000
b110110 %
b110110 C
b10000100 ,
b10000100 5
0*
#70625
1*
#71250
b110111 %
b110111 C
b10000011 ,
b10000011 5
0*
#71875
1*
#72500
b111000 %
b111000 C
0*
#73125
1*
#73750
b111001 %
b111001 C
b10000100 ,
b10000100 5
0*
#74375
1*
#75000
b111010 %
b111010 C
b10000101 ,
b10000101 5
0*
#75625
1*
#76250
b111011 %
b111011 C
b10000100 ,
b10000100 5
0*
#76875
1*
#77500
b111100 %
b111100 C
b10000011 ,
b10000011 5
0*
#78125
1*
#78750
b111101 %
b111101 C
b10000110 ,
b10000110 5
0*
#79375
1*
#80000
b111110 %
b111110 C
b10000111 ,
b10000111 5
0*
#80625
1*
#81250
b111111 %
b111111 C
b10000101 ,
b10000101 5
0*
#81875
1*
#82500
b1000000 %
b1000000 C
b10000100 ,
b10000100 5
0*
#83125
1*
#83750
b1000001 %
b1000001 C
b10001001 ,
b10001001 5
0*
#84375
1*
#85000
b1000010 %
b1000010 C
b10000001 ,
b10000001 5
0*
#85625
1*
#86250
b1000011 %
b1000011 C
b10000011 ,
b10000011 5
0*
#86875
1*
#87500
b1000100 %
b1000100 C
0*
#88125
1*
#88750
b1000101 %
b1000101 C
b10000010 ,
b10000010 5
0*
#89375
1*
#90000
b1000110 %
b1000110 C
b10000011 ,
b10000011 5
0*
#90625
1*
#91250
b1000111 %
b1000111 C
b10000001 ,
b10000001 5
0*
#91875
1*
#92500
b1001000 %
b1001000 C
b10000010 ,
b10000010 5
0*
#93125
1*
#93750
b1001001 %
b1001001 C
0*
#94375
1*
#95000
b1001010 %
b1001010 C
b10000001 ,
b10000001 5
0*
#95625
1*
#96250
b1001011 %
b1001011 C
b1111111 ,
b1111111 5
0*
#96875
1*
#97500
b1001100 %
b1001100 C
b10000000 ,
b10000000 5
0*
#98125
1*
#98750
b1001101 %
b1001101 C
b1111011 ,
b1111011 5
0*
#99375
1*
#100000
b1001110 %
b1001110 C
b1111001 ,
b1111001 5
0*
#100625
1*
#101250
b1001111 %
b1001111 C
b1110011 ,
b1110011 5
0*
#101875
1*
#102500
b1010000 %
b1010000 C
b1101011 ,
b1101011 5
0*
#103125
1*
#103750
b1010001 %
b1010001 C
b1110001 ,
b1110001 5
0*
#104375
1*
#105000
b1010010 %
b1010010 C
b10000100 ,
b10000100 5
0*
#105625
1*
#106250
b1010011 %
b1010011 C
b10010001 ,
b10010001 5
0*
#106875
1*
#107500
b1010100 %
b1010100 C
b10011010 ,
b10011010 5
0*
#108125
1*
#108750
b1010101 %
b1010101 C
b10100000 ,
b10100000 5
0*
#109375
1*
#110000
b1010110 %
b1010110 C
b10011111 ,
b10011111 5
0*
#110625
1*
#111250
b1010111 %
b1010111 C
b10010110 ,
b10010110 5
0*
#111875
1*
#112500
b1011000 %
b1011000 C
b10011001 ,
b10011001 5
0*
#113125
1*
#113750
b1011001 %
b1011001 C
b10011010 ,
b10011010 5
0*
#114375
1*
#115000
b1011010 %
b1011010 C
b10011011 ,
b10011011 5
0*
#115625
1*
#116250
b1011011 %
b1011011 C
b10011101 ,
b10011101 5
0*
#116875
1*
#117500
b1011100 %
b1011100 C
b10011010 ,
b10011010 5
0*
#118125
1*
#118750
b1011101 %
b1011101 C
b10011001 ,
b10011001 5
0*
#119375
1*
#120000
b1011110 %
b1011110 C
0*
#120625
1*
#121250
b1011111 %
b1011111 C
0*
#121875
1*
#122500
b1100000 %
b1100000 C
0*
#123125
1*
#123750
b1100001 %
b1100001 C
b10011100 ,
b10011100 5
0*
#124375
1*
#125000
b1100010 %
b1100010 C
0*
#125625
1*
#126250
b1100011 %
b1100011 C
b10011110 ,
b10011110 5
0*
#126875
1*
#127500
b1100100 %
b1100100 C
b10011011 ,
b10011011 5
0*
#128125
1*
#128750
b1100101 %
b1100101 C
b10100001 ,
b10100001 5
0*
#129375
1*
#130000
b1100110 %
b1100110 C
b11001001 ,
b11001001 5
0*
#130625
1*
#131250
b1100111 %
b1100111 C
b11010101 ,
b11010101 5
0*
#131875
1*
#132500
b1101000 %
b1101000 C
b11011010 ,
b11011010 5
0*
#133125
1*
#133750
b1101001 %
b1101001 C
b11010101 ,
b11010101 5
0*
#134375
1*
#135000
b1101010 %
b1101010 C
b10100000 ,
b10100000 5
0*
#135625
1*
#136250
b1101011 %
b1101011 C
b1101000 ,
b1101000 5
0*
#136875
1*
#137500
b1101100 %
b1101100 C
b1101100 ,
b1101100 5
0*
#138125
1*
#138750
b1101101 %
b1101101 C
b1110101 ,
b1110101 5
0*
#139375
1*
#140000
b1101110 %
b1101110 C
b1111001 ,
b1111001 5
0*
#140625
1*
#141250
b1101111 %
b1101111 C
0*
#141875
1*
#142500
b1110000 %
b1110000 C
0*
#143125
1*
#143750
b1110001 %
b1110001 C
b1111101 ,
b1111101 5
0*
#144375
1*
#145000
b1110010 %
b1110010 C
b1111001 ,
b1111001 5
0*
#145625
1*
#146250
b1110011 %
b1110011 C
b1111010 ,
b1111010 5
0*
#146875
1*
#147500
b1110100 %
b1110100 C
0*
#148125
1*
#148750
b1110101 %
b1110101 C
b1111100 ,
b1111100 5
0*
#149375
1*
#150000
b1110110 %
b1110110 C
b1111101 ,
b1111101 5
0*
#150625
1*
#151250
b1110111 %
b1110111 C
0*
#151875
1*
#152500
b1111000 %
b1111000 C
b1111001 ,
b1111001 5
0*
#153125
1*
#153750
b1111001 %
b1111001 C
b1111110 ,
b1111110 5
0*
#154375
1*
#155000
b1111010 %
b1111010 C
b1111111 ,
b1111111 5
0*
#155625
1*
#156250
b1111011 %
b1111011 C
b1111101 ,
b1111101 5
0*
#156875
1*
#157500
b1111100 %
b1111100 C
b1111100 ,
b1111100 5
0*
#158125
1*
#158750
b1111101 %
b1111101 C
b1110101 ,
b1110101 5
0*
#159375
1*
#160000
b1111110 %
b1111110 C
b1110111 ,
b1110111 5
0*
#160625
1*
#161250
b1111111 %
b1111111 C
b10100000 ,
b10100000 5
0*
#161875
1*
#162500
b10000000 %
b10000000 C
b10011100 ,
b10011100 5
0*
#163125
1*
#163750
b10000001 %
b10000001 C
b10100000 ,
b10100000 5
0*
#164375
0>
1=
bx011x 6
1<
1*
#165000
b10000010 %
b10000010 C
b10011111 ,
b10011111 5
0*
#165625
bx0011x 6
0?
1*
#166250
b10000011 %
b10000011 C
b10100000 ,
b10100000 5
0*
#166875
1*
#167500
b10000100 %
b10000100 C
b10011011 ,
b10011011 5
0*
#168125
1*
#168750
b10000101 %
b10000101 C
b10011100 ,
b10011100 5
0*
#169375
1*
#170000
b10000110 %
b10000110 C
b10011010 ,
b10011010 5
0*
#170625
1*
#171250
b10000111 %
b10000111 C
0*
#171875
1*
#172500
b10001000 %
b10001000 C
b10011011 ,
b10011011 5
0*
#173125
1*
#173750
b10001001 %
b10001001 C
0*
#174375
1*
#175000
b10001010 %
b10001010 C
b10100010 ,
b10100010 5
0*
#175625
1*
#176250
b10001011 %
b10001011 C
b10101000 ,
b10101000 5
0*
#176875
1*
#177500
b10001100 %
b10001100 C
b10101101 ,
b10101101 5
0*
#178125
1*
#178750
b10001101 %
b10001101 C
b10101100 ,
b10101100 5
0*
#179375
1*
#180000
b10001110 %
b10001110 C
b10100011 ,
b10100011 5
0*
#180625
1*
#181250
b10001111 %
b10001111 C
b10010000 ,
b10010000 5
0*
#181875
1*
#182500
b10010000 %
b10010000 C
b1110100 ,
b1110100 5
0*
#183125
1*
#183750
b10010001 %
b10010001 C
b1011110 ,
b1011110 5
0*
#184375
1*
#185000
b10010010 %
b10010010 C
0*
#185625
1*
#186250
b10010011 %
b10010011 C
b1100100 ,
b1100100 5
0*
#186875
1*
#187500
b10010100 %
b10010100 C
b1101011 ,
b1101011 5
0*
#188125
1*
#188750
b10010101 %
b10010101 C
b1101001 ,
b1101001 5
0*
#189375
1*
#190000
b10010110 %
b10010110 C
0*
#190625
1*
#191250
b10010111 %
b10010111 C
0*
#191875
1*
#192500
b10011000 %
b10011000 C
b1101011 ,
b1101011 5
0*
#193125
1*
#193750
b10011001 %
b10011001 C
0*
#194375
1*
#195000
b10011010 %
b10011010 C
b1101010 ,
b1101010 5
0*
#195625
1*
#196250
b10011011 %
b10011011 C
b1101110 ,
b1101110 5
0*
#196875
1*
#197500
b10011100 %
b10011100 C
b1110110 ,
b1110110 5
0*
#198125
1*
#198750
b10011101 %
b10011101 C
b1111001 ,
b1111001 5
0*
#199375
1*
#200000
b10011110 %
b10011110 C
b1111100 ,
b1111100 5
0*
#200625
1*
#201250
b10011111 %
b10011111 C
b1111101 ,
b1111101 5
0*
#201875
1*
#202500
b10100000 %
b10100000 C
b1111110 ,
b1111110 5
0*
#203125
1*
#203750
b10100001 %
b10100001 C
b10000011 ,
b10000011 5
0*
#204375
1*
#205000
b10100010 %
b10100010 C
b10000010 ,
b10000010 5
0*
#205625
1*
#206250
b10100011 %
b10100011 C
b10000011 ,
b10000011 5
0*
#206875
1*
#207500
b10100100 %
b10100100 C
0*
#208125
1*
#208750
b10100101 %
b10100101 C
0*
#209375
1*
#210000
b10100110 %
b10100110 C
0*
#210625
1*
#211250
b10100111 %
b10100111 C
b10000010 ,
b10000010 5
0*
#211875
1*
#212500
b10101000 %
b10101000 C
b10000101 ,
b10000101 5
0*
#213125
1*
#213750
b10101001 %
b10101001 C
0*
#214375
1*
#215000
b10101010 %
b10101010 C
b10000111 ,
b10000111 5
0*
#215625
1*
#216250
b10101011 %
b10101011 C
b10000101 ,
b10000101 5
0*
#216875
1*
#217500
b10101100 %
b10101100 C
b10000110 ,
b10000110 5
0*
#218125
1*
#218750
b10101101 %
b10101101 C
0*
#219375
1*
#220000
b10101110 %
b10101110 C
b10000100 ,
b10000100 5
0*
#220625
1*
#221250
b10101111 %
b10101111 C
0*
#221875
1*
#222500
b10110000 %
b10110000 C
0*
#223125
1*
#223750
b10110001 %
b10110001 C
b10000110 ,
b10000110 5
0*
#224375
1*
#225000
b10110010 %
b10110010 C
b10000101 ,
b10000101 5
0*
#225625
1*
#226250
b10110011 %
b10110011 C
b10000110 ,
b10000110 5
0*
#226875
1*
#227500
b10110100 %
b10110100 C
b10000101 ,
b10000101 5
0*
#228125
1*
#228750
b10110101 %
b10110101 C
b10000110 ,
b10000110 5
0*
#229375
1*
#230000
b10110110 %
b10110110 C
b10000100 ,
b10000100 5
0*
#230625
1*
#231250
b10110111 %
b10110111 C
b10000010 ,
b10000010 5
0*
#231875
1*
#232500
b10111000 %
b10111000 C
b10000011 ,
b10000011 5
0*
#233125
1*
#233750
b10111001 %
b10111001 C
b10000100 ,
b10000100 5
0*
#234375
1*
#235000
b10111010 %
b10111010 C
0*
#235625
1*
#236250
b10111011 %
b10111011 C
b10000010 ,
b10000010 5
0*
#236875
1*
#237500
b10111100 %
b10111100 C
b10000011 ,
b10000011 5
0*
#238125
1*
#238750
b10111101 %
b10111101 C
b10000101 ,
b10000101 5
0*
#239375
1*
#240000
b10111110 %
b10111110 C
0*
#240625
1*
#241250
b10111111 %
b10111111 C
b10000100 ,
b10000100 5
0*
#241875
1*
#242500
b11000000 %
b11000000 C
0*
#243125
1*
#243750
b11000001 %
b11000001 C
b10000110 ,
b10000110 5
0*
#244375
1*
#245000
b11000010 %
b11000010 C
b10000010 ,
b10000010 5
0*
#245625
1*
#246250
b11000011 %
b11000011 C
b10000001 ,
b10000001 5
0*
#246875
1*
#247500
b11000100 %
b11000100 C
b10000010 ,
b10000010 5
0*
#248125
1*
#248750
b11000101 %
b11000101 C
b10000001 ,
b10000001 5
0*
#249375
1*
#250000
b11000110 %
b11000110 C
b10000010 ,
b10000010 5
0*
#250625
1*
#251250
b11000111 %
b11000111 C
b1111111 ,
b1111111 5
0*
#251875
1*
#252500
b11001000 %
b11001000 C
b10000010 ,
b10000010 5
0*
#253125
1*
#253750
b11001001 %
b11001001 C
0*
#254375
1*
#255000
b11001010 %
b11001010 C
b10000001 ,
b10000001 5
0*
#255625
1*
#256250
b11001011 %
b11001011 C
b10000000 ,
b10000000 5
0*
#256875
1*
#257500
b11001100 %
b11001100 C
b1111110 ,
b1111110 5
0*
#258125
1*
#258750
b11001101 %
b11001101 C
b1111011 ,
b1111011 5
0*
#259375
1*
#260000
b11001110 %
b11001110 C
b1111000 ,
b1111000 5
0*
#260625
1*
#261250
b11001111 %
b11001111 C
b1110011 ,
b1110011 5
0*
#261875
1*
#262500
b11010000 %
b11010000 C
b1101011 ,
b1101011 5
0*
#263125
1*
#263750
b11010001 %
b11010001 C
b1101110 ,
b1101110 5
0*
#264375
1*
#265000
b11010010 %
b11010010 C
b10000001 ,
b10000001 5
0*
#265625
1*
#266250
b11010011 %
b11010011 C
b10001111 ,
b10001111 5
0*
#266875
1*
#267500
b11010100 %
b11010100 C
b10011001 ,
b10011001 5
0*
#268125
1*
#268750
b11010101 %
b11010101 C
b10011111 ,
b10011111 5
0*
#269375
1*
#270000
b11010110 %
b11010110 C
b10011110 ,
b10011110 5
0*
#270625
1*
