my note/ic競賽/106初賽/mytest/LCD_CTRL.v
`define IMAGE "image2.dat"

module LCD_CTRL(clk,
            reset,
            cmd,
            cmd_valid,
            IROM_Q,
            IROM_rd,
            IROM_A,
            IRAM_valid,
            IRAM_D,
            IRAM_A,
            busy,
            done);
    input clk;
    input reset;
    input [3:0] cmd;
    input cmd_valid;
    input [7:0] IROM_Q;
    output IROM_rd;
    output [5:0] IROM_A;
    output IRAM_valid;
    output [7:0] IRAM_D;
    output [5:0] IRAM_A;
    output busy;
    output done;
    /*****************************************************************
                              declaration    
    *****************************************************************/
    //parameter
    parameter READ_IMG = 0;
    parameter READ_CMD = 1;
    parameter OP = 2;
    parameter WRITE = 3;
    
    //reg and wire
    reg [1:0] state_cr;
    reg [1:0] state_nt;
    reg [7:0] img_buffer [0:63];
    reg [5:0] RAM_counter;
    reg [5:0] op_point1;
    reg [7:0] max_point;
    reg [7:0] min_point;
    reg [9:0] avr_buf;
    wire [5:0] op_point2;
    wire [5:0] op_point3;
    wire [5:0] op_point4;

    reg IROM_rd;
    reg [5:0] IROM_A;
    reg IRAM_valid;
    reg [7:0] IRAM_D;
    reg [5:0] IRAM_A;
    reg busy;
    reg done;

    /*****************************************************************
                                 state machine    
    *****************************************************************/
    always@(posedge clk or posedge reset)begin
        if(reset)
            state_cr <= READ_IMG;
        else 
            state_cr <= state_nt;
    end

    always@(*)begin
        if(reset)
            state_nt = READ_IMG;
        else begin
            case(state_cr)
                READ_IMG:begin
                    if(IROM_A == 6'd63) state_nt = READ_CMD;
                    else state_nt = READ_IMG;
                end
                READ_CMD:begin
                    if(cmd_valid && cmd != 4'd0) state_nt = OP;
                    else if (cmd_valid && cmd == 4'd0) state_nt = WRITE;
                    else state_nt = READ_CMD;
                end
                OP:begin
                    state_nt = READ_CMD;
                end
                WRITE:begin
                    state_nt = WRITE;
                end
                default:
                    state_cr = READ_IMG;
            endcase
        end
    end
    /*****************************************************************
                                    output    
    *****************************************************************/
    //state output
    always@(*)begin
        case(state_cr)
            READ_IMG:begin
                IROM_rd =   1'b1;
                IRAM_valid =1'b0;
                busy =      1'b1;
            end
            READ_CMD:begin
                IROM_rd =   1'b0;
                IRAM_valid =1'b0;
                busy =      1'b0;
            end
            OP:begin
                IROM_rd =   1'b0;
                IRAM_valid =1'b0;
                busy =      1'b1;
            end
            WRITE:begin
                IROM_rd =   1'b0;
                IRAM_valid =1'b1;
                busy =      1'b1;
            end
            default:begin
                IROM_rd =   1'b0;
                IRAM_valid =1'b0;
                busy =      1'b0;
            end
        endcase
    end

    //IROM_A
    always@(posedge clk or posedge reset)begin
        if(reset)begin
            IROM_A <= 6'd0;
        end
        else if(IROM_rd) begin
            if(IROM_A == 6'd63) IROM_A <= 6'd0;
            else IROM_A <= IROM_A + 6'd1;
        end
        else begin
            IROM_A <= IROM_A;
        end 
    end

    //IRAM_A
    always@(posedge clk or posedge reset)begin
        if(reset)begin
            RAM_counter <= 6'd0;
        end
        else if(state_cr == WRITE) begin
            if(RAM_counter == 6'd63) RAM_counter <= RAM_counter;
            else RAM_counter <= RAM_counter + 1;
        end
        else begin
            RAM_counter <= RAM_counter;
        end 
    end
    
    always@(posedge clk or posedge reset)begin
        if(reset)begin
            IRAM_A <= 6'd0;
        end
        else begin
            IRAM_A <= RAM_counter;
        end 
    end

    //IRAM_D
    always@(posedge clk)begin
        if(state_cr == WRITE) begin
            IRAM_D <= img_buffer[RAM_counter];
        end
        else begin
            IRAM_D <= IRAM_D;
        end
    end
    //done
    always @(posedge clk)
    begin
        if (IRAM_A == 6'd63) done <= 1'd1;
        else done <= 1'd0;
    end 
    /*****************************************************************
                                    option    
    *****************************************************************/
    assign op_point2 = op_point1 + 6'd1;
    assign op_point3 = op_point1 + 6'd8;
    assign op_point4 = op_point1 + 6'd9;

    //op_point
    always@(posedge clk)begin
        if(reset)begin
            op_point1 <= 6'h1b;
        end
        else if(state_cr == READ_CMD)begin
            case(cmd)
                //shift up
                4'b0001:begin
                    if(op_point1 == 6'h0 || op_point1 == 6'h1 || op_point1 == 6'h2 || op_point1 == 6'h3 || op_point1 == 6'h4 || op_point1 == 6'h5 || op_point1 == 6'h6)begin
                        op_point1 <= op_point1;
                    end
                    else begin
                        op_point1 <= op_point1 - 6'd8;
                    end
                end
                //shift down
                4'b0010:begin
                    if(op_point1 == 6'h30 || op_point1 == 6'h31 || op_point1 == 6'h32 || op_point1 == 6'h33 || op_point1 == 6'h34 || op_point1 == 6'h35 || op_point1 == 6'h36)begin
                        op_point1 <= op_point1;
                    end
                    else begin
                        op_point1 <= op_point1 + 6'd8;
                    end
                end
                //shift left
                4'b0011:begin
                    if(op_point1 == 6'h0 || op_point1 == 6'h8 || op_point1 == 6'h10 || op_point1 == 6'h18 || op_point1 == 6'h20 || op_point1 == 6'h28 || op_point1 == 6'h30)begin
                        op_point1 <= op_point1;
                    end
                    else begin
                        op_point1 <= op_point1 - 6'd1;
                    end
                end
                //shift right
                4'b0100:begin
                    if(op_point1 == 6'h6 || op_point1 == 6'he || op_point1 == 6'h16 || op_point1 == 6'h1e || op_point1 == 6'h26 || op_point1 == 6'h2e || op_point1 == 6'h36)begin
                        op_point1 <= op_point1;
                    end
                    else begin
                        op_point1 <= op_point1 + 6'd1;
                    end
                end
                //default
                default:begin
                    op_point1 <= op_point1;
                end
            endcase
        end
    end

    //max
    always@(*)begin
        if(img_buffer[op_point1] >= img_buffer[op_point2] && img_buffer[op_point1] >= img_buffer[op_point3] && img_buffer[op_point1] >= img_buffer[op_point4])begin
            max_point <= op_point1;
        end
        else if(img_buffer[op_point2] >= img_buffer[op_point1] && img_buffer[op_point2] >= img_buffer[op_point3] && img_buffer[op_point2] >= img_buffer[op_point4])begin
            max_point <= op_point2;
        end
        else if(img_buffer[op_point3] >= img_buffer[op_point1] && img_buffer[op_point3] >= img_buffer[op_point2] && img_buffer[op_point3] >= img_buffer[op_point4])begin
            max_point <= op_point3;
        end
        else begin
            max_point <= op_point4;
        end
    end

    //min
    always@(*)begin
        if(img_buffer[op_point1] <= img_buffer[op_point2] && img_buffer[op_point1] <= img_buffer[op_point3] && img_buffer[op_point1] <= img_buffer[op_point4])begin
            min_point <= op_point1;
        end
        else if(img_buffer[op_point2] <= img_buffer[op_point1] && img_buffer[op_point2] <= img_buffer[op_point3] && img_buffer[op_point2] <= img_buffer[op_point4])begin
            min_point <= op_point2;
        end
        else if(img_buffer[op_point3] <= img_buffer[op_point1] && img_buffer[op_point3] <= img_buffer[op_point2] && img_buffer[op_point3] <= img_buffer[op_point4])begin
            min_point <= op_point3;
        end
        else begin
            min_point <= op_point4;
        end
    end

    //average
    always@(*)begin
        avr_buf <= img_buffer[op_point1] + img_buffer[op_point2] + img_buffer[op_point3] + img_buffer[op_point4];
    end

    /*****************************************************************
                                    img buffer    
    *****************************************************************/
    //img_buffer
    always@(posedge clk)begin
        case(state_cr)
            READ_IMG:begin
                if(IROM_rd == 1'b1) img_buffer[IROM_A] <= IROM_Q;
            end
            READ_CMD:begin
                case(cmd)
                    //max
                    4'b0101:begin
                        img_buffer[op_point1] <= img_buffer[max_point];
                        img_buffer[op_point2] <= img_buffer[max_point];
                        img_buffer[op_point3] <= img_buffer[max_point];
                        img_buffer[op_point4] <= img_buffer[max_point];
                    end
                    //min
                    4'b0110:begin
                        img_buffer[op_point1] <= img_buffer[min_point];
                        img_buffer[op_point2] <= img_buffer[min_point];
                        img_buffer[op_point3] <= img_buffer[min_point];
                        img_buffer[op_point4] <= img_buffer[min_point];
                    end
                    //average
                    4'b0111:begin
                        img_buffer[op_point1] <= avr_buf[9:2];
                        img_buffer[op_point2] <= avr_buf[9:2];
                        img_buffer[op_point3] <= avr_buf[9:2];
                        img_buffer[op_point4] <= avr_buf[9:2];
                    end
                    //counterclockwise rotation
                    4'b1000:begin
                        img_buffer[op_point1] <= img_buffer[op_point2];
                        img_buffer[op_point2] <= img_buffer[op_point4];
                        img_buffer[op_point3] <= img_buffer[op_point1];
                        img_buffer[op_point4] <= img_buffer[op_point3];
                    end
                    //clockwise rotation
                    4'b1001:begin
                        img_buffer[op_point1] <= img_buffer[op_point3];
                        img_buffer[op_point2] <= img_buffer[op_point1];
                        img_buffer[op_point3] <= img_buffer[op_point4];
                        img_buffer[op_point4] <= img_buffer[op_point2];
                    end
                    //mirror x
                    4'b1010:begin                        
                        img_buffer[op_point1] <= img_buffer[op_point3];
                        img_buffer[op_point2] <= img_buffer[op_point4];
                        img_buffer[op_point3] <= img_buffer[op_point1];
                        img_buffer[op_point4] <= img_buffer[op_point2];
                    end
                    //mirror y
                    4'b1011:begin
                        img_buffer[op_point1] <= img_buffer[op_point2];
                        img_buffer[op_point2] <= img_buffer[op_point1];
                        img_buffer[op_point3] <= img_buffer[op_point4];
                        img_buffer[op_point4] <= img_buffer[op_point3];
                    end
                    default:begin
                        img_buffer[op_point1] <= img_buffer[op_point1];
                        img_buffer[op_point2] <= img_buffer[op_point2];
                        img_buffer[op_point3] <= img_buffer[op_point3];
                        img_buffer[op_point4] <= img_buffer[op_point4];
                    end
                endcase    
            end
        endcase
    end

endmodule

mytest/ic競賽/106初賽/mytest/LCD_CTRL_tb.v
`timescale 1ns/10ps
`define CYCLE    10.0         	        // Modify your clock period here

`include "LCD_CTRL.v"

`define SDFFILE  "./LCD_CTRL_syn.sdf"	// Modify your sdf file name

/*`ifdef tb1
  `define EXPECT "./tb1_goal.dat"
  `define CMD "./cmd1.dat"
  `define IMAGE "image1.dat"
`endif*/

//`ifdef tb2
  `define EXPECT "./tb2_goal.dat"
  `define CMD "./cmd2.dat"
  `define IMAGE "image2.dat"
//`endif

/*`ifdef tb3
  `define EXPECT "./tb3_goal.dat"
  `define CMD "./cmd3.dat"
  `define IMAGE "image3.dat"
`endif*/


module LCD_CTRL_tb;
parameter IMAGE_N_PAT = 64;
parameter CMD_N_PAT = 46;
parameter t_reset = `CYCLE*2;


reg clk;
reg reset;
reg [6:0] err_IRAM;
reg [3:0] cmd;
reg cmd_valid;
reg [7:0]  out_mem[0:63];


wire IROM_rd;
wire [5:0] IROM_A;
wire IRAM_valid;
wire [7:0] IRAM_D;
wire [5:0] IRAM_A;
wire busy;
wire done;
wire [7:0]  IROM_Q;


integer i, j, k, l, err;

reg over;
reg   [3:0]   cmd_mem   [0:CMD_N_PAT-1];



	LCD_CTRL LCD_CTRL(.clk(clk), .reset(reset), 
		     .cmd(cmd), .cmd_valid(cmd_valid), 
                     .IROM_rd(IROM_rd), .IROM_A(IROM_A), .IROM_Q(IROM_Q), 
                     .IRAM_valid(IRAM_valid), .IRAM_D(IRAM_D), .IRAM_A(IRAM_A),
		     .busy(busy), .done(done));

	IROM  IROM_1(.IROM_rd(IROM_rd), .IROM_data(IROM_Q), .IROM_addr(IROM_A), .clk(clk), .reset(reset));

	IRAM IRAM_1 (.clk(clk), .IRAM_data(IRAM_D), .IRAM_addr(IRAM_A), .IRAM_valid(IRAM_valid));


//initial $sdf_annotate(`SDFFILE, top);

`ifdef SDF
	initial $sdf_annotate(`SDFFILE, LCD_CTRL);
`endif

initial	$readmemh (`CMD,    cmd_mem);
//initial	$readmemh (`EXPECT, out_mem);

initial begin

//$fsdbDumpfile("LCD_CTRL.fsdb");
//$fsdbDumpvars;
//$fsdbDumpMDA;
end





initial begin
   clk         = 1'b0;
   reset       = 1'b0;
   over	       = 1'b0;
   l	       = 0;
   err         = 0;   
end

always begin #(`CYCLE/2) clk = ~clk; end

initial begin
   @(negedge clk)  reset = 1'b1;
   #t_reset        reset = 1'b0;
                                  
end  

            
 always @(negedge clk)
begin

	begin
	if (l < CMD_N_PAT)
	begin
		if(!busy) 
		begin
        	cmd = cmd_mem[l];
        	cmd_valid = 1'b1;
		l=l+1;
		end  
		else
		cmd_valid = 1'b0;
	end
	else
	begin
		l=l;
		cmd_valid = 1'b0;
	end
	end
end


initial @(posedge done) 
begin
   for(k=0;k<64;k=k+1)begin
         if( IRAM_1.IRAM_M[k] !== out_mem[k]) 
		begin
         	$display("ERROR at %d:output %h !=expect %h ",k, IRAM_1.IRAM_M[k], out_mem[k]);
         	err = err+1 ;
		end
         else if ( out_mem[k] === 8'dx)
                begin
                $display("ERROR at %d:output %h !=expect %h ",k, IRAM_1.IRAM_M[k], out_mem[k]);
		err=err+1;
                end   
 over=1'b1;
end
        begin
	if (err === 0 &&  over===1'b1  )  begin
	            $display("All data have been generated successfully!\n");
	            $display("-------------------PASS-------------------\n");
		    #10 $finish;
	         end
	         else if( over===1'b1 )
		 begin 
	            $display("There are %d errors!\n", err);
	            $display("---------------------------------------------\n");
		    #10 $finish;
         	 end
	
	end
end

initial begin
	$dumpfile("wave.vcd");
	$dumpvars(0, LCD_CTRL_tb);
end

endmodule


//-----------------------------------------------------------------------
//-----------------------------------------------------------------------
module IROM (IROM_rd, IROM_data, IROM_addr, clk, reset);
input		IROM_rd;
input	[5:0] 	IROM_addr;
output	[7:0]	IROM_data;
input		clk, reset;

reg [7:0] sti_M [0:63];
integer i;

reg	[7:0]	IROM_data;

initial begin
	@ (negedge reset) $readmemb (`IMAGE , sti_M);
	end

always@(negedge clk) 
	if (IROM_rd) IROM_data <= sti_M[IROM_addr];
	
endmodule



//-----------------------------------------------------------------------
//-----------------------------------------------------------------------

module IRAM (IRAM_valid, IRAM_data, IRAM_addr, clk);
input		IRAM_valid;
input	[5:0] 	IRAM_addr;
input	[7:0]	IRAM_data;
input		clk;

reg [7:0] IRAM_M [0:63];
integer i;

initial begin
	for (i=0; i<=63; i=i+1) IRAM_M[i] = 0;
end

always@(negedge clk) 
	if (IRAM_valid) IRAM_M[ IRAM_addr ] <= IRAM_data;

endmodule

//-----------------------------------------------------------------------
//-----------------------------------------------------------------------

my note/ic競賽/106初賽/mytest/wave.vcd
$date
	Mon Feb 03 16:41:21 2025
$end
$version
	Icarus Verilog
$end
$timescale
	10ps
$end
$scope module LCD_CTRL_tb $end
$var wire 1 ! done $end
$var wire 1 " busy $end
$var wire 1 # IROM_rd $end
$var wire 8 $ IROM_Q [7:0] $end
$var wire 6 % IROM_A [5:0] $end
$var wire 1 & IRAM_valid $end
$var wire 8 ' IRAM_D [7:0] $end
$var wire 6 ( IRAM_A [5:0] $end
$var parameter 32 ) CMD_N_PAT $end
$var parameter 32 * IMAGE_N_PAT $end
$var real 1 + t_reset $end
$var reg 1 , clk $end
$var reg 4 - cmd [3:0] $end
$var reg 1 . cmd_valid $end
$var reg 1 / over $end
$var reg 1 0 reset $end
$var integer 32 1 err [31:0] $end
$var integer 32 2 k [31:0] $end
$var integer 32 3 l [31:0] $end
$scope module IRAM_1 $end
$var wire 1 , clk $end
$var wire 1 & IRAM_valid $end
$var wire 8 4 IRAM_data [7:0] $end
$var wire 6 5 IRAM_addr [5:0] $end
$var integer 32 6 i [31:0] $end
$upscope $end
$scope module IROM_1 $end
$var wire 1 , clk $end
$var wire 1 0 reset $end
$var wire 1 # IROM_rd $end
$var wire 6 7 IROM_addr [5:0] $end
$var reg 8 8 IROM_data [7:0] $end
$upscope $end
$scope module LCD_CTRL $end
$var wire 8 9 IROM_Q [7:0] $end
$var wire 1 , clk $end
$var wire 4 : cmd [3:0] $end
$var wire 1 . cmd_valid $end
$var wire 1 0 reset $end
$var wire 6 ; op_point4 [5:0] $end
$var wire 6 < op_point3 [5:0] $end
$var wire 6 = op_point2 [5:0] $end
$var parameter 32 > OP $end
$var parameter 32 ? READ_CMD $end
$var parameter 32 @ READ_IMG $end
$var parameter 32 A WRITE $end
$var reg 6 B IRAM_A [5:0] $end
$var reg 8 C IRAM_D [7:0] $end
$var reg 1 & IRAM_valid $end
$var reg 6 D IROM_A [5:0] $end
$var reg 1 # IROM_rd $end
$var reg 6 E RAM_counter [5:0] $end
$var reg 10 F avr_buf [9:0] $end
$var reg 1 " busy $end
$var reg 1 ! done $end
$var reg 8 G max_point [7:0] $end
$var reg 8 H min_point [7:0] $end
$var reg 6 I op_point1 [5:0] $end
$var reg 2 J state_cr [1:0] $end
$var reg 2 K state_nt [1:0] $end
$upscope $end
$upscope $end
$enddefinitions $end
$comment Show the parameter values. $end
$dumpall
b11 A
b0 @
b1 ?
b10 >
r20 +
b1000000 *
b101110 )
$end
#0
$dumpvars
bx K
b0 J
bx I
bx H
bx G
bx F
bx E
bx D
bx C
bx B
bx =
bx <
bx ;
bx :
bx 9
bx 8
bx 7
b1000000 6
bx 5
bx 4
b0 3
bx 2
b0 1
00
0/
x.
bx -
0,
bx (
bx '
0&
bx %
bx $
1#
1"
x!
$end
#500
0!
b0 J
1,
#1000
b0 (
b0 5
b0 B
b0 E
b0 %
b0 7
b0 D
b0 K
10
0.
0,
#1500
b100100 H
b100100 G
b11100 =
b100011 <
b100100 ;
b11011 I
1,
#2000
b0 $
b0 8
b0 9
0,
#2500
1,
#3000
0,
00
#3500
b1 %
b1 7
b1 D
1,
#4000
b1 $
b1 8
b1 9
0,
#4500
b10 %
b10 7
b10 D
1,
#5000
b10 $
b10 8
b10 9
0,
#5500
b11 %
b11 7
b11 D
1,
#6000
b11 $
b11 8
b11 9
0,
#6500
b100 %
b100 7
b100 D
1,
#7000
b100 $
b100 8
b100 9
0,
#7500
b101 %
b101 7
b101 D
1,
#8000
b101 $
b101 8
b101 9
0,
#8500
b110 %
b110 7
b110 D
1,
#9000
b110 $
b110 8
b110 9
0,
#9500
b111 %
b111 7
b111 D
1,
#10000
b111 $
b111 8
b111 9
0,
#10500
b1000 %
b1000 7
b1000 D
1,
#11000
b1000 $
b1000 8
b1000 9
0,
#11500
b1001 %
b1001 7
b1001 D
1,
#12000
b1001 $
b1001 8
b1001 9
0,
#12500
b1010 %
b1010 7
b1010 D
1,
#13000
b1010 $
b1010 8
b1010 9
0,
#13500
b1011 %
b1011 7
b1011 D
1,
#14000
b1011 $
b1011 8
b1011 9
0,
#14500
b1100 %
b1100 7
b1100 D
1,
#15000
b1100 $
b1100 8
b1100 9
0,
#15500
b1101 %
b1101 7
b1101 D
1,
#16000
b1101 $
b1101 8
b1101 9
0,
#16500
b1110 %
b1110 7
b1110 D
1,
#17000
b1110 $
b1110 8
b1110 9
0,
#17500
b1111 %
b1111 7
b1111 D
1,
#18000
b1111 $
b1111 8
b1111 9
0,
#18500
b10000 %
b10000 7
b10000 D
1,
#19000
b10000 $
b10000 8
b10000 9
0,
#19500
b10001 %
b10001 7
b10001 D
1,
#20000
b10001 $
b10001 8
b10001 9
0,
#20500
b10010 %
b10010 7
b10010 D
1,
#21000
b10010 $
b10010 8
b10010 9
0,
#21500
b10011 %
b10011 7
b10011 D
1,
#22000
b10011 $
b10011 8
b10011 9
0,
#22500
b10100 %
b10100 7
b10100 D
1,
#23000
b10100 $
b10100 8
b10100 9
0,
#23500
b10101 %
b10101 7
b10101 D
1,
#24000
b10101 $
b10101 8
b10101 9
0,
#24500
b10110 %
b10110 7
b10110 D
1,
#25000
b10110 $
b10110 8
b10110 9
0,
#25500
b10111 %
b10111 7
b10111 D
1,
#26000
b10111 $
b10111 8
b10111 9
0,
#26500
b11000 %
b11000 7
b11000 D
1,
#27000
b11000 $
b11000 8
b11000 9
0,
#27500
b11001 %
b11001 7
b11001 D
1,
#28000
b11001 $
b11001 8
b11001 9
0,
#28500
b11010 %
b11010 7
b11010 D
1,
#29000
b11010 $
b11010 8
b11010 9
0,
#29500
b11011 %
b11011 7
b11011 D
1,
#30000
b11011 $
b11011 8
b11011 9
0,
#30500
b11100 %
b11100 7
b11100 D
1,
#31000
b11100 $
b11100 8
b11100 9
0,
#31500
b11101 %
b11101 7
b11101 D
1,
#32000
b11101 $
b11101 8
b11101 9
0,
#32500
b11110 %
b11110 7
b11110 D
1,
#33000
b11110 $
b11110 8
b11110 9
0,
#33500
b11111 %
b11111 7
b11111 D
1,
#34000
b11111 $
b11111 8
b11111 9
0,
#34500
b100000 %
b100000 7
b100000 D
1,
#35000
b100000 $
b100000 8
b100000 9
0,
#35500
b100001 %
b100001 7
b100001 D
1,
#36000
b100001 $
b100001 8
b100001 9
0,
#36500
b100010 %
b100010 7
b100010 D
1,
#37000
b100010 $
b100010 8
b100010 9
0,
#37500
b100011 %
b100011 7
b100011 D
1,
#38000
b100011 $
b100011 8
b100011 9
0,
#38500
b100100 %
b100100 7
b100100 D
1,
#39000
b100100 $
b100100 8
b100100 9
0,
#39500
b11011 H
b1111110 F
b100101 %
b100101 7
b100101 D
1,
#40000
b100101 $
b100101 8
b100101 9
0,
#40500
b100110 %
b100110 7
b100110 D
1,
#41000
b100110 $
b100110 8
b100110 9
0,
#41500
b100111 %
b100111 7
b100111 D
1,
#42000
b100111 $
b100111 8
b100111 9
0,
#42500
b101000 %
b101000 7
b101000 D
1,
#43000
b101000 $
b101000 8
b101000 9
0,
#43500
b101001 %
b101001 7
b101001 D
1,
#44000
b101001 $
b101001 8
b101001 9
0,
#44500
b101010 %
b101010 7
b101010 D
1,
#45000
b101010 $
b101010 8
b101010 9
0,
#45500
b101011 %
b101011 7
b101011 D
1,
#46000
b101011 $
b101011 8
b101011 9
0,
#46500
b101100 %
b101100 7
b101100 D
1,
#47000
b101100 $
b101100 8
b101100 9
0,
#47500
b101101 %
b101101 7
b101101 D
1,
#48000
b101101 $
b101101 8
b101101 9
0,
#48500
b101110 %
b101110 7
b101110 D
1,
#49000
b101110 $
b101110 8
b101110 9
0,
#49500
b101111 %
b101111 7
b101111 D
1,
#50000
b101111 $
b101111 8
b101111 9
0,
#50500
b110000 %
b110000 7
b110000 D
1,
#51000
b110000 $
b110000 8
b110000 9
0,
#51500
b110001 %
b110001 7
b110001 D
1,
#52000
b110001 $
b110001 8
b110001 9
0,
#52500
b110010 %
b110010 7
b110010 D
1,
#53000
b110010 $
b110010 8
b110010 9
0,
#53500
b110011 %
b110011 7
b110011 D
1,
#54000
b110011 $
b110011 8
b110011 9
0,
#54500
b110100 %
b110100 7
b110100 D
1,
#55000
b110100 $
b110100 8
b110100 9
0,
#55500
b110101 %
b110101 7
b110101 D
1,
#56000
b110101 $
b110101 8
b110101 9
0,
#56500
b110110 %
b110110 7
b110110 D
1,
#57000
b110110 $
b110110 8
b110110 9
0,
#57500
b110111 %
b110111 7
b110111 D
1,
#58000
b110111 $
b110111 8
b110111 9
0,
#58500
b111000 %
b111000 7
b111000 D
1,
#59000
b111000 $
b111000 8
b111000 9
0,
#59500
b111001 %
b111001 7
b111001 D
1,
#60000
b111001 $
b111001 8
b111001 9
0,
#60500
b111010 %
b111010 7
b111010 D
1,
#61000
b111010 $
b111010 8
b111010 9
0,
#61500
b111011 %
b111011 7
b111011 D
1,
#62000
b111011 $
b111011 8
b111011 9
0,
#62500
b111100 %
b111100 7
b111100 D
1,
#63000
b111100 $
b111100 8
b111100 9
0,
#63500
b111101 %
b111101 7
b111101 D
1,
#64000
b111101 $
b111101 8
b111101 9
0,
#64500
b111110 %
b111110 7
b111110 D
1,
#65000
b111110 $
b111110 8
b111110 9
0,
#65500
b1 K
b111111 %
b111111 7
b111111 D
1,
#66000
b111111 $
b111111 8
b111111 9
0,
#66500
0"
0#
b0 %
b0 7
b0 D
b1 J
1,
#67000
b10 K
b1 3
1.
b11 -
b11 :
0,
#67500
b100011 G
b11010 H
b1111010 F
1"
b1 K
b11011 =
b100010 <
b100011 ;
b11010 I
b10 J
1,
#68000
0.
0,
#68500
0"
b1 J
1,
#69000
b10 K
b10 3
1.
b101 -
b101 :
0,
#69500
b10001100 F
b11010 G
1"
b1 K
b10 J
1,
#70000
0.
0,
#70500
0"
b1 J
1,
#71000
b10 K
b11 3
1.
b1 -
b1 :
0,
#71500
b10010 H
b1101011 F
1"
b1 K
b10011 =
b11010 <
b11011 ;
b10010 I
b10 J
1,
#72000
0.
0,
#72500
0"
b1 J
1,
#73000
b10 K
b100 3
1.
b1000 -
b1000 :
0,
#73500
b11010 H
b10011 G
1"
b1 K
b10 J
1,
#74000
0.
0,
#74500
0"
b1 J
1,
#75000
b10 K
b101 3
1.
b100 -
b100 :
0,
#75500
b10100 H
b1110110 F
1"
b1 K
b10100 =
b11011 <
b11100 ;
b10011 I
b10 J
1,
#76000
0.
0,
#76500
0"
b1 J
1,
#77000
b10 K
b110 3
1.
b1010 -
b1010 :
0,
#77500
b11100 H
1"
b1 K
b10 J
1,
#78000
0.
0,
#78500
0"
b1 J
1,
#79000
b10 K
b111 3
1.
b10 -
b10 :
0,
#79500
b100100 G
b1111110 F
1"
b1 K
b11100 =
b100011 <
b100100 ;
b11011 I
b10 J
1,
#80000
0.
0,
#80500
0"
b1 J
1,
#81000
b10 K
b1000 3
1.
b1001 -
b1001 :
0,
#81500
b100100 H
b100011 G
1"
b1 K
b10 J
1,
#82000
0.
0,
#82500
0"
b1 J
1,
#83000
b10 K
b1001 3
1.
b100 -
b100 :
0,
#83500
b100101 G
b1111001 F
1"
b1 K
b11101 =
b100100 <
b100101 ;
b11100 I
b10 J
1,
#84000
0.
0,
#84500
0"
b1 J
1,
#85000
b10 K
b1010 3
1.
b110 -
b110 :
0,
#85500
b1010000 F
b11100 H
b11100 G
1"
b1 K
b10 J
1,
#86000
0.
0,
#86500
0"
b1 J
1,
#87000
b10 K
b1011 3
1.
b10 -
b10 :
0,
#87500
b101101 G
b100100 H
b10000001 F
1"
b1 K
b100101 =
b101100 <
b101101 ;
b100100 I
b10 J
1,
#88000
0.
0,
#88500
0"
b1 J
1,
#89000
b10 K
b1100 3
1.
b111 -
b111 :
0,
#89500
b10000000 F
b100100 G
1"
b1 K
b10 J
1,
#90000
0.
0,
#90500
0"
b1 J
1,
#91000
b10 K
b1101 3
1.
b11 -
b11 :
0,
#91500
b101011 G
b10001111 F
1"
b1 K
b100100 =
b101011 <
b101100 ;
b100011 I
b10 J
1,
#92000
0.
0,
#92500
0"
b1 J
1,
#93000
b10 K
b1110 3
1.
b1011 -
b1011 :
0,
#93500
b100011 H
b101100 G
1"
b1 K
b10 J
1,
#94000
0.
0,
#94500
0"
b1 J
1,
#95000
b11 K
b1111 3
1.
b0 -
b0 :
0,
#95500
1"
1&
b11 J
1,
#96000
0.
0,
#96500
b0 '
b0 4
b0 C
b1 E
1,
#97000
0,
#97500
b1 '
b1 4
b1 C
b10 E
b1 (
b1 5
b1 B
1,
#98000
0,
#98500
b10 '
b10 4
b10 C
b10 (
b10 5
b10 B
b11 E
1,
#99000
0,
#99500
b11 '
b11 4
b11 C
b100 E
b11 (
b11 5
b11 B
1,
#100000
0,
#100500
b100 '
b100 4
b100 C
b100 (
b100 5
b100 B
b101 E
1,
#101000
0,
#101500
b101 '
b101 4
b101 C
b110 E
b101 (
b101 5
b101 B
1,
#102000
0,
#102500
b110 '
b110 4
b110 C
b110 (
b110 5
b110 B
b111 E
1,
#103000
0,
#103500
b111 '
b111 4
b111 C
b1000 E
b111 (
b111 5
b111 B
1,
#104000
0,
#104500
b1000 '
b1000 4
b1000 C
b1000 (
b1000 5
b1000 B
b1001 E
1,
#105000
0,
#105500
b1001 '
b1001 4
b1001 C
b1010 E
b1001 (
b1001 5
b1001 B
1,
#106000
0,
#106500
b1010 '
b1010 4
b1010 C
b1010 (
b1010 5
b1010 B
b1011 E
1,
#107000
0,
#107500
b1011 '
b1011 4
b1011 C
b1100 E
b1011 (
b1011 5
b1011 B
1,
#108000
0,
#108500
b1100 '
b1100 4
b1100 C
b1100 (
b1100 5
b1100 B
b1101 E
1,
#109000
0,
#109500
b1101 '
b1101 4
b1101 C
b1110 E
b1101 (
b1101 5
b1101 B
1,
#110000
0,
#110500
b1110 '
b1110 4
b1110 C
b1110 (
b1110 5
b1110 B
b1111 E
1,
#111000
0,
#111500
b1111 '
b1111 4
b1111 C
b10000 E
b1111 (
b1111 5
b1111 B
1,
#112000
0,
#112500
b10000 '
b10000 4
b10000 C
b10000 (
b10000 5
b10000 B
b10001 E
1,
#113000
0,
#113500
b10001 '
b10001 4
b10001 C
b10010 E
b10001 (
b10001 5
b10001 B
1,
#114000
0,
#114500
b10011 '
b10011 4
b10011 C
b10010 (
b10010 5
b10010 B
b10011 E
1,
#115000
0,
#115500
b100011 '
b100011 4
b100011 C
b10100 E
b10011 (
b10011 5
b10011 B
1,
#116000
0,
#116500
b11100 '
b11100 4
b11100 C
b10100 (
b10100 5
b10100 B
b10101 E
1,
#117000
0,
#117500
b10101 '
b10101 4
b10101 C
b10110 E
b10101 (
b10101 5
b10101 B
1,
#118000
0,
#118500
b10110 '
b10110 4
b10110 C
b10110 (
b10110 5
b10110 B
b10111 E
1,
#119000
0,
#119500
b10111 '
b10111 4
b10111 C
b11000 E
b10111 (
b10111 5
b10111 B
1,
#120000
0,
#120500
b11000 '
b11000 4
b11000 C
b11000 (
b11000 5
b11000 B
b11001 E
1,
#121000
0,
#121500
b11001 '
b11001 4
b11001 C
b11010 E
b11001 (
b11001 5
b11001 B
1,
#122000
0,
#122500
b10010 '
b10010 4
b10010 C
b11010 (
b11010 5
b11010 B
b11011 E
1,
#123000
0,
#123500
b100011 '
b100011 4
b100011 C
b11100 E
b11011 (
b11011 5
b11011 B
1,
#124000
0,
#124500
b10100 '
b10100 4
b10100 C
b11100 (
b11100 5
b11100 B
b11101 E
1,
#125000
0,
#125500
b11110 E
b11101 (
b11101 5
b11101 B
1,
#126000
0,
#126500
b11110 '
b11110 4
b11110 C
b11110 (
b11110 5
b11110 B
b11111 E
1,
#127000
0,
#127500
b11111 '
b11111 4
b11111 C
b100000 E
b11111 (
b11111 5
b11111 B
1,
#128000
0,
#128500
b100000 '
b100000 4
b100000 C
b100000 (
b100000 5
b100000 B
b100001 E
1,
#129000
0,
#129500
b100001 '
b100001 4
b100001 C
b100010 E
b100001 (
b100001 5
b100001 B
1,
#130000
0,
#130500
b100011 '
b100011 4
b100011 C
b100010 (
b100010 5
b100010 B
b100011 E
1,
#131000
0,
